location_processor/__init__.py
location_processor/process_location.cpython-312-darwin.so
location_processor-0.2.3.dist-info/LICENSE.txt
location_processor-0.2.3.dist-info/METADATA
location_processor-0.2.3.dist-info/WHEEL
location_processor-0.2.3.dist-info/top_level.txt
location_processor-0.2.3.dist-info/RECORD
